serialize_mcr/__init__.py
serialize_mcr/const.py
serialize_mcr/hp.py
tests/__init__.py
tests/conftest.py
tests/unit/__init__.py
tests/unit/const.py
tests/unit/test_run.py
serialize_mcr-1.0.1.dist-info/LICENSE
serialize_mcr-1.0.1.dist-info/METADATA
serialize_mcr-1.0.1.dist-info/WHEEL
serialize_mcr-1.0.1.dist-info/top_level.txt
serialize_mcr-1.0.1.dist-info/RECORD
