Metadata-Version: 2.1
Name: serialize-mcr
Version: 1.0.1
Summary: Creating a serializer for data structures
Home-page: https://github.com/millcityrunner/serialize-mcr
Author: Andrew Ray
Author-email: mcaray9@gmail.com
License: MIT
Platform: UNKNOWN
Classifier: Programming Language :: Python :: 3
Classifier: License :: OSI Approved :: MIT License
Classifier: Operating System :: OS Independent
License-File: LICENSE
Requires-Dist: flask-sqlalchemy
Requires-Dist: sqlalchemy
